MANIFEST.in
setup.cfg
setup.py
authentication/__init__.py
authentication/admin.py
authentication/apps.py
authentication/models.py
authentication/tests.py
authentication/urls.py
authentication/views.py
authentication/migrations/0001_initial.py
authentication/migrations/0002_forgotpassword.py
authentication/migrations/__init__.py
authentication/templates/authentication/base.html
authentication/templates/authentication/forgot-password.html
authentication/templates/authentication/invalid.html
authentication/templates/authentication/login.html
authentication/templates/authentication/new-verify.html
authentication/templates/authentication/register.html
authentication/templates/authentication/registered.html
authentication/templates/authentication/reset-password.html
authentication/templates/authentication/success.html
django_quickauth.egg-info/PKG-INFO
django_quickauth.egg-info/SOURCES.txt
django_quickauth.egg-info/dependency_links.txt
django_quickauth.egg-info/top_level.txt